{"total":179,"engines":{"babel":0,"boa":68,"chakra":21,"engine262":0,"graaljs":178,"graaljs_exp":178,"jsc":178,"jsc_exp":178,"kiesel":1,"libjs":179,"njs":0,"nova":0,"qjs":0,"qjs_ng":0,"rhino":0,"sm":179,"sm_exp":0,"sucrase":0,"swc":0,"v8":177,"v8_exp":0,"xs":0},"files":{"intl402/NumberFormat/prototype/this-value-numberformat-prototype.js":{"total":1,"engines":{"babel":0,"boa":1,"chakra":0,"engine262":0,"graaljs":1,"graaljs_exp":1,"jsc":1,"jsc_exp":1,"kiesel":1,"libjs":1,"njs":0,"nova":0,"qjs":0,"qjs_ng":0,"rhino":0,"sm":1,"sm_exp":0,"sucrase":0,"swc":0,"v8":1,"v8_exp":0,"xs":0}},"intl402/NumberFormat/prototype/prop-desc.js":{"total":1,"engines":{"babel":0,"boa":1,"chakra":1,"engine262":0,"graaljs":1,"graaljs_exp":1,"jsc":1,"jsc_exp":1,"kiesel":0,"libjs":1,"njs":0,"nova":0,"qjs":0,"qjs_ng":0,"rhino":0,"sm":1,"sm_exp":0,"sucrase":0,"swc":0,"v8":1,"v8_exp":0,"xs":0}},"intl402/NumberFormat/prototype/builtin.js":{"total":1,"engines":{"babel":0,"boa":1,"chakra":0,"engine262":0,"graaljs":1,"graaljs_exp":1,"jsc":1,"jsc_exp":1,"kiesel":0,"libjs":1,"njs":0,"nova":0,"qjs":0,"qjs_ng":0,"rhino":0,"sm":1,"sm_exp":0,"sucrase":0,"swc":0,"v8":1,"v8_exp":0,"xs":0}},"intl402/NumberFormat/prototype/constructor":{"total":2,"engines":{"babel":0,"boa":2,"chakra":2,"engine262":0,"graaljs":2,"graaljs_exp":2,"jsc":2,"jsc_exp":2,"kiesel":0,"libjs":2,"njs":0,"nova":0,"qjs":0,"qjs_ng":0,"rhino":0,"sm":2,"sm_exp":0,"sucrase":0,"swc":0,"v8":2,"v8_exp":0,"xs":0}},"intl402/NumberFormat/prototype/format":{"total":95,"engines":{"babel":0,"boa":49,"chakra":9,"engine262":0,"graaljs":95,"graaljs_exp":95,"jsc":94,"jsc_exp":94,"kiesel":0,"libjs":95,"njs":0,"nova":0,"qjs":0,"qjs_ng":0,"rhino":0,"sm":95,"sm_exp":0,"sucrase":0,"swc":0,"v8":94,"v8_exp":0,"xs":0}},"intl402/NumberFormat/prototype/formatRange":{"total":11,"engines":{"babel":0,"boa":2,"chakra":0,"engine262":0,"graaljs":11,"graaljs_exp":11,"jsc":11,"jsc_exp":11,"kiesel":0,"libjs":11,"njs":0,"nova":0,"qjs":0,"qjs_ng":0,"rhino":0,"sm":11,"sm_exp":0,"sucrase":0,"swc":0,"v8":11,"v8_exp":0,"xs":0}},"intl402/NumberFormat/prototype/formatRangeToParts":{"total":10,"engines":{"babel":0,"boa":2,"chakra":2,"engine262":0,"graaljs":10,"graaljs_exp":10,"jsc":10,"jsc_exp":10,"kiesel":0,"libjs":10,"njs":0,"nova":0,"qjs":0,"qjs_ng":0,"rhino":0,"sm":10,"sm_exp":0,"sucrase":0,"swc":0,"v8":10,"v8_exp":0,"xs":0}},"intl402/NumberFormat/prototype/formatToParts":{"total":44,"engines":{"babel":0,"boa":1,"chakra":3,"engine262":0,"graaljs":44,"graaljs_exp":44,"jsc":44,"jsc_exp":44,"kiesel":0,"libjs":44,"njs":0,"nova":0,"qjs":0,"qjs_ng":0,"rhino":0,"sm":44,"sm_exp":0,"sucrase":0,"swc":0,"v8":44,"v8_exp":0,"xs":0}},"intl402/NumberFormat/prototype/resolvedOptions":{"total":12,"engines":{"babel":0,"boa":7,"chakra":4,"engine262":0,"graaljs":11,"graaljs_exp":11,"jsc":12,"jsc_exp":12,"kiesel":0,"libjs":12,"njs":0,"nova":0,"qjs":0,"qjs_ng":0,"rhino":0,"sm":12,"sm_exp":0,"sucrase":0,"swc":0,"v8":11,"v8_exp":0,"xs":0}},"intl402/NumberFormat/prototype/toStringTag":{"total":2,"engines":{"babel":0,"boa":2,"chakra":0,"engine262":0,"graaljs":2,"graaljs_exp":2,"jsc":2,"jsc_exp":2,"kiesel":0,"libjs":2,"njs":0,"nova":0,"qjs":0,"qjs_ng":0,"rhino":0,"sm":2,"sm_exp":0,"sucrase":0,"swc":0,"v8":2,"v8_exp":0,"xs":0}}}}