{"total":15,"engines":{"babel":0,"boa":15,"chakra":0,"engine262":0,"graaljs":15,"graaljs_exp":15,"jsc":15,"jsc_exp":15,"kiesel":15,"libjs":1,"njs":0,"nova":4,"qjs":1,"qjs_ng":15,"rhino":0,"sm":15,"sm_exp":0,"sucrase":0,"swc":0,"v8":15,"v8_exp":0,"xs":15},"files":{"built-ins/SharedArrayBuffer/prototype/grow/grow-larger-size.js":{"total":1,"engines":{"babel":0,"boa":1,"chakra":0,"engine262":0,"graaljs":1,"graaljs_exp":1,"jsc":1,"jsc_exp":1,"kiesel":1,"libjs":0,"njs":0,"nova":0,"qjs":0,"qjs_ng":1,"rhino":0,"sm":1,"sm_exp":0,"sucrase":0,"swc":0,"v8":1,"v8_exp":0,"xs":1}},"built-ins/SharedArrayBuffer/prototype/grow/extensible.js":{"total":1,"engines":{"babel":0,"boa":1,"chakra":0,"engine262":0,"graaljs":1,"graaljs_exp":1,"jsc":1,"jsc_exp":1,"kiesel":1,"libjs":0,"njs":0,"nova":1,"qjs":0,"qjs_ng":1,"rhino":0,"sm":1,"sm_exp":0,"sucrase":0,"swc":0,"v8":1,"v8_exp":0,"xs":1}},"built-ins/SharedArrayBuffer/prototype/grow/descriptor.js":{"total":1,"engines":{"babel":0,"boa":1,"chakra":0,"engine262":0,"graaljs":1,"graaljs_exp":1,"jsc":1,"jsc_exp":1,"kiesel":1,"libjs":0,"njs":0,"nova":1,"qjs":0,"qjs_ng":1,"rhino":0,"sm":1,"sm_exp":0,"sucrase":0,"swc":0,"v8":1,"v8_exp":0,"xs":1}},"built-ins/SharedArrayBuffer/prototype/grow/grow-same-size.js":{"total":1,"engines":{"babel":0,"boa":1,"chakra":0,"engine262":0,"graaljs":1,"graaljs_exp":1,"jsc":1,"jsc_exp":1,"kiesel":1,"libjs":0,"njs":0,"nova":0,"qjs":0,"qjs_ng":1,"rhino":0,"sm":1,"sm_exp":0,"sucrase":0,"swc":0,"v8":1,"v8_exp":0,"xs":1}},"built-ins/SharedArrayBuffer/prototype/grow/length.js":{"total":1,"engines":{"babel":0,"boa":1,"chakra":0,"engine262":0,"graaljs":1,"graaljs_exp":1,"jsc":1,"jsc_exp":1,"kiesel":1,"libjs":0,"njs":0,"nova":1,"qjs":0,"qjs_ng":1,"rhino":0,"sm":1,"sm_exp":0,"sucrase":0,"swc":0,"v8":1,"v8_exp":0,"xs":1}},"built-ins/SharedArrayBuffer/prototype/grow/grow-smaller-size.js":{"total":1,"engines":{"babel":0,"boa":1,"chakra":0,"engine262":0,"graaljs":1,"graaljs_exp":1,"jsc":1,"jsc_exp":1,"kiesel":1,"libjs":0,"njs":0,"nova":0,"qjs":0,"qjs_ng":1,"rhino":0,"sm":1,"sm_exp":0,"sucrase":0,"swc":0,"v8":1,"v8_exp":0,"xs":1}},"built-ins/SharedArrayBuffer/prototype/grow/new-length-excessive.js":{"total":1,"engines":{"babel":0,"boa":1,"chakra":0,"engine262":0,"graaljs":1,"graaljs_exp":1,"jsc":1,"jsc_exp":1,"kiesel":1,"libjs":0,"njs":0,"nova":0,"qjs":0,"qjs_ng":1,"rhino":0,"sm":1,"sm_exp":0,"sucrase":0,"swc":0,"v8":1,"v8_exp":0,"xs":1}},"built-ins/SharedArrayBuffer/prototype/grow/name.js":{"total":1,"engines":{"babel":0,"boa":1,"chakra":0,"engine262":0,"graaljs":1,"graaljs_exp":1,"jsc":1,"jsc_exp":1,"kiesel":1,"libjs":0,"njs":0,"nova":1,"qjs":0,"qjs_ng":1,"rhino":0,"sm":1,"sm_exp":0,"sucrase":0,"swc":0,"v8":1,"v8_exp":0,"xs":1}},"built-ins/SharedArrayBuffer/prototype/grow/new-length-non-number.js":{"total":1,"engines":{"babel":0,"boa":1,"chakra":0,"engine262":0,"graaljs":1,"graaljs_exp":1,"jsc":1,"jsc_exp":1,"kiesel":1,"libjs":0,"njs":0,"nova":0,"qjs":0,"qjs_ng":1,"rhino":0,"sm":1,"sm_exp":0,"sucrase":0,"swc":0,"v8":1,"v8_exp":0,"xs":1}},"built-ins/SharedArrayBuffer/prototype/grow/new-length-negative.js":{"total":1,"engines":{"babel":0,"boa":1,"chakra":0,"engine262":0,"graaljs":1,"graaljs_exp":1,"jsc":1,"jsc_exp":1,"kiesel":1,"libjs":0,"njs":0,"nova":0,"qjs":0,"qjs_ng":1,"rhino":0,"sm":1,"sm_exp":0,"sucrase":0,"swc":0,"v8":1,"v8_exp":0,"xs":1}},"built-ins/SharedArrayBuffer/prototype/grow/this-is-not-arraybuffer-object.js":{"total":1,"engines":{"babel":0,"boa":1,"chakra":0,"engine262":0,"graaljs":1,"graaljs_exp":1,"jsc":1,"jsc_exp":1,"kiesel":1,"libjs":0,"njs":0,"nova":0,"qjs":0,"qjs_ng":1,"rhino":0,"sm":1,"sm_exp":0,"sucrase":0,"swc":0,"v8":1,"v8_exp":0,"xs":1}},"built-ins/SharedArrayBuffer/prototype/grow/nonconstructor.js":{"total":1,"engines":{"babel":0,"boa":1,"chakra":0,"engine262":0,"graaljs":1,"graaljs_exp":1,"jsc":1,"jsc_exp":1,"kiesel":1,"libjs":0,"njs":0,"nova":0,"qjs":0,"qjs_ng":1,"rhino":0,"sm":1,"sm_exp":0,"sucrase":0,"swc":0,"v8":1,"v8_exp":0,"xs":1}},"built-ins/SharedArrayBuffer/prototype/grow/this-is-not-resizable-arraybuffer-object.js":{"total":1,"engines":{"babel":0,"boa":1,"chakra":0,"engine262":0,"graaljs":1,"graaljs_exp":1,"jsc":1,"jsc_exp":1,"kiesel":1,"libjs":0,"njs":0,"nova":0,"qjs":0,"qjs_ng":1,"rhino":0,"sm":1,"sm_exp":0,"sucrase":0,"swc":0,"v8":1,"v8_exp":0,"xs":1}},"built-ins/SharedArrayBuffer/prototype/grow/this-is-not-object.js":{"total":1,"engines":{"babel":0,"boa":1,"chakra":0,"engine262":0,"graaljs":1,"graaljs_exp":1,"jsc":1,"jsc_exp":1,"kiesel":1,"libjs":0,"njs":0,"nova":0,"qjs":0,"qjs_ng":1,"rhino":0,"sm":1,"sm_exp":0,"sucrase":0,"swc":0,"v8":1,"v8_exp":0,"xs":1}},"built-ins/SharedArrayBuffer/prototype/grow/this-is-sharedarraybuffer.js":{"total":1,"engines":{"babel":0,"boa":1,"chakra":0,"engine262":0,"graaljs":1,"graaljs_exp":1,"jsc":1,"jsc_exp":1,"kiesel":1,"libjs":1,"njs":0,"nova":0,"qjs":1,"qjs_ng":1,"rhino":0,"sm":1,"sm_exp":0,"sucrase":0,"swc":0,"v8":1,"v8_exp":0,"xs":1}}}}