{"total":78,"engines":{"babel":61,"boa":0,"chakra":0,"engine262":0,"graaljs":0,"graaljs_exp":0,"jsc":0,"jsc_exp":0,"kiesel":0,"libjs":78,"njs":0,"nova":0,"qjs":0,"qjs_ng":0,"rhino":0,"sm":78,"sm_exp":0,"sucrase":0,"swc":61,"v8":78,"v8_exp":0,"xs":78},"files":{"built-ins/DisposableStack/prototype/Symbol.dispose.js":{"total":1,"engines":{"babel":1,"boa":0,"chakra":0,"engine262":0,"graaljs":0,"graaljs_exp":0,"jsc":0,"jsc_exp":0,"kiesel":0,"libjs":1,"njs":0,"nova":0,"qjs":0,"qjs_ng":0,"rhino":0,"sm":1,"sm_exp":0,"sucrase":0,"swc":1,"v8":1,"v8_exp":0,"xs":1}},"built-ins/DisposableStack/prototype/Symbol.toStringTag.js":{"total":1,"engines":{"babel":1,"boa":0,"chakra":0,"engine262":0,"graaljs":0,"graaljs_exp":0,"jsc":0,"jsc_exp":0,"kiesel":0,"libjs":1,"njs":0,"nova":0,"qjs":0,"qjs_ng":0,"rhino":0,"sm":1,"sm_exp":0,"sucrase":0,"swc":1,"v8":1,"v8_exp":0,"xs":1}},"built-ins/DisposableStack/prototype/constructor.js":{"total":1,"engines":{"babel":1,"boa":0,"chakra":0,"engine262":0,"graaljs":0,"graaljs_exp":0,"jsc":0,"jsc_exp":0,"kiesel":0,"libjs":1,"njs":0,"nova":0,"qjs":0,"qjs_ng":0,"rhino":0,"sm":1,"sm_exp":0,"sucrase":0,"swc":1,"v8":1,"v8_exp":0,"xs":1}},"built-ins/DisposableStack/prototype/prop-desc.js":{"total":1,"engines":{"babel":1,"boa":0,"chakra":0,"engine262":0,"graaljs":0,"graaljs_exp":0,"jsc":0,"jsc_exp":0,"kiesel":0,"libjs":1,"njs":0,"nova":0,"qjs":0,"qjs_ng":0,"rhino":0,"sm":1,"sm_exp":0,"sucrase":0,"swc":1,"v8":1,"v8_exp":0,"xs":1}},"built-ins/DisposableStack/prototype/proto.js":{"total":1,"engines":{"babel":1,"boa":0,"chakra":0,"engine262":0,"graaljs":0,"graaljs_exp":0,"jsc":0,"jsc_exp":0,"kiesel":0,"libjs":1,"njs":0,"nova":0,"qjs":0,"qjs_ng":0,"rhino":0,"sm":1,"sm_exp":0,"sucrase":0,"swc":1,"v8":1,"v8_exp":0,"xs":1}},"built-ins/DisposableStack/prototype/adopt":{"total":11,"engines":{"babel":8,"boa":0,"chakra":0,"engine262":0,"graaljs":0,"graaljs_exp":0,"jsc":0,"jsc_exp":0,"kiesel":0,"libjs":11,"njs":0,"nova":0,"qjs":0,"qjs_ng":0,"rhino":0,"sm":11,"sm_exp":0,"sucrase":0,"swc":8,"v8":11,"v8_exp":0,"xs":11}},"built-ins/DisposableStack/prototype/defer":{"total":10,"engines":{"babel":7,"boa":0,"chakra":0,"engine262":0,"graaljs":0,"graaljs_exp":0,"jsc":0,"jsc_exp":0,"kiesel":0,"libjs":10,"njs":0,"nova":0,"qjs":0,"qjs_ng":0,"rhino":0,"sm":10,"sm_exp":0,"sucrase":0,"swc":7,"v8":10,"v8_exp":0,"xs":10}},"built-ins/DisposableStack/prototype/dispose":{"total":13,"engines":{"babel":10,"boa":0,"chakra":0,"engine262":0,"graaljs":0,"graaljs_exp":0,"jsc":0,"jsc_exp":0,"kiesel":0,"libjs":13,"njs":0,"nova":0,"qjs":0,"qjs_ng":0,"rhino":0,"sm":13,"sm_exp":0,"sucrase":0,"swc":10,"v8":13,"v8_exp":0,"xs":13}},"built-ins/DisposableStack/prototype/disposed":{"total":7,"engines":{"babel":5,"boa":0,"chakra":0,"engine262":0,"graaljs":0,"graaljs_exp":0,"jsc":0,"jsc_exp":0,"kiesel":0,"libjs":7,"njs":0,"nova":0,"qjs":0,"qjs_ng":0,"rhino":0,"sm":7,"sm_exp":0,"sucrase":0,"swc":5,"v8":7,"v8_exp":0,"xs":7}},"built-ins/DisposableStack/prototype/move":{"total":13,"engines":{"babel":10,"boa":0,"chakra":0,"engine262":0,"graaljs":0,"graaljs_exp":0,"jsc":0,"jsc_exp":0,"kiesel":0,"libjs":13,"njs":0,"nova":0,"qjs":0,"qjs_ng":0,"rhino":0,"sm":13,"sm_exp":0,"sucrase":0,"swc":10,"v8":13,"v8_exp":0,"xs":13}},"built-ins/DisposableStack/prototype/use":{"total":19,"engines":{"babel":16,"boa":0,"chakra":0,"engine262":0,"graaljs":0,"graaljs_exp":0,"jsc":0,"jsc_exp":0,"kiesel":0,"libjs":19,"njs":0,"nova":0,"qjs":0,"qjs_ng":0,"rhino":0,"sm":19,"sm_exp":0,"sucrase":0,"swc":16,"v8":19,"v8_exp":0,"xs":19}}}}